ctestgen/__init__.py
ctestgen/generator/__init__.py
ctestgen/generator/arrays_test_generator.py
ctestgen/generator/c_control_structures.py
ctestgen/generator/c_macros.py
ctestgen/generator/c_operators.py
ctestgen/generator/c_std_constants.py
ctestgen/generator/c_std_functions.py
ctestgen/generator/c_structure_elements.py
ctestgen/generator/c_types.py
ctestgen/generator/generator.py
ctestgen/generator/style_parametres.py
ctestgen/generator/templates.py
ctestgen/generator/utils.py
ctestgen/runner/__init__.py
ctestgen/runner/basic_test_runner.py
ctestgen/runner/runner.py
ctestgen/runner/utils.py
ctestgen-0.1.2.dist-info/LICENSE
ctestgen-0.1.2.dist-info/METADATA
ctestgen-0.1.2.dist-info/WHEEL
ctestgen-0.1.2.dist-info/top_level.txt
ctestgen-0.1.2.dist-info/RECORD
