Metadata-Version: 2.1
Name: ctestgen
Version: 0.1.2
Summary: https://github.com/VolandTymim/ctestgen
Home-page: https://github.com/VolandTymim/ctestgen
Author: Vasilkin Vladislav
Author-email: volandtymim@gmail.com
License: UNKNOWN
Keywords: python c code-generation code-generator autotesting
Platform: UNKNOWN
Classifier: Programming Language :: Python :: 3.6
Classifier: License :: OSI Approved :: MIT License
Classifier: Operating System :: OS Independent
